sausage/__init__.py
sausage-0.0.1.dist-info/METADATA
sausage-0.0.1.dist-info/WHEEL
sausage-0.0.1.dist-info/top_level.txt
sausage-0.0.1.dist-info/RECORD
